setup.py
voluum/__init__.py
voluum/client.py
voluum.egg-info/PKG-INFO
voluum.egg-info/SOURCES.txt
voluum.egg-info/dependency_links.txt
voluum.egg-info/top_level.txt